pydcm2png/__init__.py
pydcm2png/_dcm2png.so
pydcm2png/dcm2png.py
pydcm2png/dicom.dic
pydcm2png/pydcm2png.py
pydcm2png-0.1.0.1.dist-info/LICENSE
pydcm2png-0.1.0.1.dist-info/METADATA
pydcm2png-0.1.0.1.dist-info/WHEEL
pydcm2png-0.1.0.1.dist-info/top_level.txt
pydcm2png-0.1.0.1.dist-info/RECORD
