Metadata-Version: 2.1
Name: pydcm2png
Version: 0.1.0.1
Summary: Get Device Independent Pixel Data From DICOM File
Home-page: https://github.com
Author: dingyuguo
Author-email: dyg1993@foxmail.com
License: UNKNOWN
Platform: UNKNOWN
Classifier: Development Status :: 4 - Beta
Classifier: Intended Audience :: Science/Research
Classifier: Intended Audience :: Developers
Classifier: License :: OSI Approved
Classifier: Programming Language :: C++
Classifier: Programming Language :: Python
Classifier: Topic :: Software Development
Classifier: Topic :: Scientific/Engineering
Classifier: Operating System :: Microsoft :: Windows
Classifier: Operating System :: POSIX
Classifier: Operating System :: Unix
Classifier: Operating System :: MacOS
Requires-Dist: numpy (>=1.15.0)
